setup.py
pipeables/__init__.py
pipeables/adwords.py
pipeables/base.py
pipeables/command_line.py
pipeables/dbs.py
pipeables/googleAnalytics.py
pipeables/helpers.py
pipeables/hive.py
pipeables/jdbc.py
pipeables/postgres.py
pipeables/presto.py
pipeables/rest.py
pipeables.egg-info/PKG-INFO
pipeables.egg-info/SOURCES.txt
pipeables.egg-info/dependency_links.txt
pipeables.egg-info/entry_points.txt
pipeables.egg-info/not-zip-safe
pipeables.egg-info/requires.txt
pipeables.egg-info/top_level.txt