Metadata-Version: 1.0
Name: pipeables
Version: 0.1.45
Summary: Simiple queries and piping between different data sources
Home-page: https://bitbucket.org/tdoran/pipeables/branch/v2package
Author: Tony Doran
Author-email: tdoran@atlassian.com
License: MIT
Platform: UNKNOWN
